aidockermon/__init__.py
aidockermon/aidockermon.py
aidockermon/handlers.py
aidockermon/settings.py
aidockermon/utils.py
etc/__init__.py
etc/config.yml
etc/mappings.json
etc/cron.d/aidockermon
etc/grafana/grafana.json
etc/syslog-ng/syslog-ng.conf
aidockermon-0.10.3.dist-info/LICENSE
aidockermon-0.10.3.dist-info/METADATA
aidockermon-0.10.3.dist-info/WHEEL
aidockermon-0.10.3.dist-info/entry_points.txt
aidockermon-0.10.3.dist-info/top_level.txt
aidockermon-0.10.3.dist-info/RECORD
