Metadata-Version: 2.1
Name: aidockermon
Version: 0.10.3
Summary: Monitor system load of the server running the nvidia/cuda docker containers.
Home-page: https://github.com/WqyJh/aidockermon
Author: wqy
Author-email: qiyingwangwqy@gmail.com
License: UNKNOWN
Keywords: docker,nvidia/cuda,linux,monitor
Platform: UNKNOWN
Classifier: Operating System :: POSIX :: Linux
Classifier: Programming Language :: Python :: 3
Classifier: Programming Language :: Python :: 3.4
Classifier: Programming Language :: Python :: 3.5
Classifier: Programming Language :: Python :: 3.6
Requires-Dist: certifi (==2019.3.9)
Requires-Dist: chardet (==3.0.4)
Requires-Dist: docker (==3.7.2)
Requires-Dist: docker-pycreds (==0.4.0)
Requires-Dist: idna (==2.8)
Requires-Dist: psutil (==5.6.1)
Requires-Dist: pytz (==2018.9)
Requires-Dist: pyyaml (==5.1)
Requires-Dist: requests (==2.21.0)
Requires-Dist: rfc5424-logging-handler (==1.4.1)
Requires-Dist: six (==1.12.0)
Requires-Dist: tzlocal (==1.5.1)
Requires-Dist: urllib3 (==1.24.1)
Requires-Dist: websocket-client (==0.56.0)
